{"status":"200","msg":"ok","data":[{"id":"9038809","goods_name":"\u65e5\u672c\u4ee3\u8d2d\u5927\u521b\u7f8e\u767d\u7cbe\u534e\u4e09\u4ef6\u5957\u5168\u8eab\u6c34\u4e73\u4e73\u6db2\u5316\u5986\u6c34\u5957\u88c5\u53bb\u5370\u62a4\u80a4","goods_id":"571312556415","cate_id":"5","cate_name":"\u7f8e\u5986","goods_url":"https:\/\/detail.tmall.com\/item.htm?id=571312556415","pic":"http:\/\/img.alicdn.com\/imgextra\/i3\/1045689065\/TB2a1Lzo2iSBuNkSnhJXXbDcpXa_!!1045689065.jpg","price":"49.9","price_after_coupons":"44.9","price_coupons":"5.0","sales":"541","rate":"24.0","commission_type":"1","commission_type_name":"\u5b9a\u5411","quan_link":"https:\/\/uland.taobao.com\/quan\/detail?sellerId=1045689065&activityId=50037263f9014c81866721e03c17e8cf","seller_id":"","quan_id":"","quan_shengyu":"99986","quan_zhong":"100000","quan_ling":"0","quan_expired_time":"2018-10-04 23:59:59","quan_note":"49","quan_guid_content":"\u65e5\u672c\u4ee3\u8d2d\u5927\u521b\u7f8e\u767d\u7cbe\u534e\u4e09\u4ef6\u5957\u5168\u8eab\u6c34\u4e73\u4e73\u6db2\u5316\u5986\u6c34\u5957\u88c5\u53bb\u5370\u62a4\u80a4","quan_qq_img":"http:\/\/images.jbkuan.com\/20180928\/de7fd5a1194336122820b767dfbc24d4.jpg_250x250.jpg","src":"0","jhs":"0","tqg":"0","gold":"0","freight":"0","abroad":"0","flagship":"0"},{"id":"9030925","goods_name":"\u65b0\u52a0\u5761\u4ee3\u8d2dchrels&kaiah\u5973\u5305\u5c0f ck2-20160\u6d41\u82cf\u9152\u7ea2\u94fe\u6761\u4fe1\u5c01\u5c0f\u65b9\u5305","goods_id":"576067278759","cate_id":"7","cate_name":"\u978b\u5305\u670d\u9970","goods_url":"https:\/\/detail.tmall.com\/item.htm?id=576067278759","pic":"http:\/\/img.alicdn.com\/imgextra\/i4\/138722161\/O1CN011RpmLmnC4o2wgQm_!!138722161.jpg","price":258,"price_after_coupons":178,"price_coupons":"80.0","sales":"112","rate":"20.1","commission_type":"1","commission_type_name":"\u5b9a\u5411","quan_link":"https:\/\/uland.taobao.com\/quan\/detail?sellerId=138722161&activityId=95d3e3f028d44d22bc0fdd17668677ea","seller_id":"","quan_id":"","quan_shengyu":"94000","quan_zhong":"100000","quan_ling":"0","quan_expired_time":"2018-09-28 23:59:59","quan_note":"180","quan_guid_content":"\u3010\u5168\u5e97\u94fa\u901a\u7528\u5377\u3011\u7cbe\u9009\u4f18\u8d28\u9762\u6599\uff0c\u505a\u5de5\u7cbe\u81f4\uff0c\u5c0f\u8eab\u6750\u5927\u5bb9\u91cf\uff0c\u5c0f\u5de7\u5b9e\u7528\uff0c\u7b80\u7ea6\u767e\u642d\uff0c\u65f6\u5c1a\u51fa\u884c\uff0c\u5973\u795e\u5fc5\u5907\u4e4b\u9009","quan_qq_img":"http:\/\/images.jbkuan.com\/20180928\/77974a774e390a8b01d4748ee4b7a634.jpg_250x250.jpg","src":"0","jhs":"0","tqg":"0","gold":"0","freight":"0","abroad":"1","flagship":"0"},{"id":"9021987","goods_name":"\u6cf0\u56fd\u4e13\u67dc\u6b63\u54c1\u4ee3\u8d2dLANNA\u5170\u7eb3\u8db3\u8d34\u690d\u7269\u914d\u65b9\u6e7f\u5bd2\u7761\u77201\u530510\u72474\u530570\u5143","goods_id":"556514430888","cate_id":"5","cate_name":"\u7f8e\u5986","goods_url":"https:\/\/item.taobao.com\/item.htm?id=556514430888","pic":"http:\/\/img.alicdn.com\/imgextra\/i4\/2189319799\/TB2659WXn1lzuRkSO8hXXXsbVXa_!!2189319799.jpg","price":60,"price_after_coupons":55,"price_coupons":"5.0","sales":"228","rate":"30.0","commission_type":"4","commission_type_name":null,"quan_link":"https:\/\/uland.taobao.com\/quan\/detail?sellerId=2189319799&activityId=1f7e08f7fcfb4cc38db1c671f8d6e53d","seller_id":"","quan_id":"","quan_shengyu":"9999","quan_zhong":"10000","quan_ling":"0","quan_expired_time":"2018-09-30 23:59:59","quan_note":"5.01","quan_guid_content":"","quan_qq_img":"http:\/\/images.jbkuan.com\/20180927\/257ad7adf426d1f80baf62549ded6668.jpg_250x250.jpg","src":"0","jhs":"0","tqg":"0","gold":"0","freight":"0","abroad":"1","flagship":"0"},{"id":"9013485","goods_name":"\u4ee3\u8d2d\u771f\u76ae\u9a6c\u4e01\u9774\u7537\u77ed\u9774\u5706\u5934\u82f1\u4f26\u98ce\u7537\u58eb\u5de5\u88c5\u9774\u6c99\u6f20\u519b\u9774\u4f11\u95f2\u9ad8\u5e2e\u7537\u978b","goods_id":"568005179970","cate_id":"7","cate_name":"\u978b\u5305\u670d\u9970","goods_url":"https:\/\/detail.tmall.com\/item.htm?id=568005179970","pic":"http:\/\/img.alicdn.com\/imgextra\/i1\/2007446250\/TB2yvaDdzQnBKNjSZSgXXXHGXXa_!!2007446250.jpg","price":560,"price_after_coupons":540,"price_coupons":"20.0","sales":"28","rate":"25.1","commission_type":"1","commission_type_name":"\u5b9a\u5411","quan_link":"https:\/\/uland.taobao.com\/quan\/detail?sellerId=2007446250&activityId=6eb04f68ce9248f59f238f3715478ef2","seller_id":"","quan_id":"","quan_shengyu":"4962","quan_zhong":"5000","quan_ling":"0","quan_expired_time":"2018-10-16 23:59:59","quan_note":"20.01","quan_guid_content":"\u771f\u76ae\u9a6c\u4e01\u9774\u7537\u77ed\u9774\uff0c\u5706\u5934\u82f1\u4f26\u98ce\uff0c\u7537\u58eb\u5de5\u88c5\u9774\uff0c\u6c99\u6f20\u519b\u9774\uff0c\u4f11\u95f2\u9ad8\u5e2e\u7537\u978b\u3002","quan_qq_img":"http:\/\/images.jbkuan.com\/20180927\/754206c75e00f0d6eed0387190237188.jpg_250x250.jpg","src":"0","jhs":"0","tqg":"0","gold":"1","freight":"0","abroad":"1","flagship":"0"},{"id":"9008865","goods_name":"\u97e9\u56fd\u4e1c\u5927\u95e8\u4ee3\u8d2d\u79cb\u51ac\u7b80\u7ea6\u6c34\u6676\u91d1\u5c5e\u8d28\u611fchic\u8033\u9489\u65f6\u5c1a\u767e\u642d\u8d85\u4ed9\u8033\u73af\u5973","goods_id":"576745152734","cate_id":"7","cate_name":"\u978b\u5305\u670d\u9970","goods_url":"https:\/\/detail.tmall.com\/item.htm?id=576745152734","pic":"http:\/\/img.alicdn.com\/imgextra\/i3\/1765467343\/O1CN012478ld7JOgZcSdg_!!1765467343.jpg","price":34,"price_after_coupons":29,"price_coupons":"5.0","sales":"820","rate":"20.0","commission_type":"4","commission_type_name":null,"quan_link":"https:\/\/uland.taobao.com\/quan\/detail?sellerId=1765467343&activityId=97783788398148608f8b1ccbe628d060","seller_id":"","quan_id":"","quan_shengyu":"8095","quan_zhong":"9999","quan_ling":"0","quan_expired_time":"2018-09-28 23:59:59","quan_note":"29","quan_guid_content":"\u97e9\u56fd\u4e1c\u5927\u95e8\u4ee3\u8d2d\u79cb\u51ac\u7b80\u7ea6\u6c34\u6676\u91d1\u5c5e\u8d28\u611fchic\u8033\u9489\u65f6\u5c1a\u767e\u642d\u8d85\u4ed9\u8033\u73af\u5973","quan_qq_img":"http:\/\/images.jbkuan.com\/20180927\/e751e227129a948424c1dc6411096e18.jpg_250x250.jpg","src":"0","jhs":"0","tqg":"0","gold":"1","freight":"0","abroad":"0","flagship":"0"},{"id":"9000555","goods_name":"\u97e9\u56fd\u4e1c\u5927\u95e8\u4ee3\u8d2d\u9ed1\u8272\u661f\u661f\u8033\u73af\u5973 \u6c14\u8d28\u957f\u6b3e925\u94f6\u6d41\u82cf\u767e\u642d\u7b80\u7ea6\u8033\u5760","goods_id":"574317981011","cate_id":"7","cate_name":"\u978b\u5305\u670d\u9970","goods_url":"https:\/\/item.taobao.com\/item.htm?id=574317981011","pic":"http:\/\/img.alicdn.com\/imgextra\/i1\/1765467343\/TB23ljRyOOYBuNjSsD4XXbSkFXa_!!1765467343.jpg","price":52,"price_after_coupons":47,"price_coupons":"5.0","sales":"1387","rate":"20.0","commission_type":"4","commission_type_name":null,"quan_link":"https:\/\/uland.taobao.com\/quan\/detail?sellerId=1765467343&activityId=8a1c873ddb72423c8f349bac62cd89e3","seller_id":"","quan_id":"","quan_shengyu":"9999","quan_zhong":"10000","quan_ling":"0","quan_expired_time":"2018-10-01 23:59:59","quan_note":"39","quan_guid_content":"\u97e9\u56fd\u4e1c\u5927\u95e8\u4ee3\u8d2d\u9ed1\u8272\u661f\u661f\u8033\u73af\uff0c\u6c14\u8d28\u957f\u6b3e\uff0c\u767e\u642d\u4e0d\u6311\u4eba\uff0c\u5f15\u4eba\u6ce8\u76ee\u4e00\u590f\uff0c\u7b80\u7ea6\u4e0d\u5931\u4e2a\u6027\uff0c\u5f20\u626c\u4e0d\u5931\u767e\u642d.","quan_qq_img":"http:\/\/images.jbkuan.com\/20180927\/536817fa08ccff0fc22033d45a77d19c.jpg_250x250.jpg","src":"0","jhs":"0","tqg":"0","gold":"1","freight":"0","abroad":"0","flagship":"0"},{"id":"8999544","goods_name":"\u65b0\u52a0\u5761\u4ee3\u8d2dchraels&kaiah\u5973\u5305\u5c0f ck2-5078\u97e9\u7248\u9ed1\u8272\u901a\u52e4\u624b\u63d0\u8033\u6735\u5305","goods_id":"576008414371","cate_id":"7","cate_name":"\u978b\u5305\u670d\u9970","goods_url":"https:\/\/detail.tmall.com\/item.htm?id=576008414371","pic":"http:\/\/gd2.alicdn.com\/imgextra\/i1\/138722161\/O1CN011RpmLpvjpuXqqim_!!138722161.jpg","price":258,"price_after_coupons":178,"price_coupons":"80.0","sales":"119","rate":"20.1","commission_type":"3","commission_type_name":"\u9e4a\u6865","quan_link":"https:\/\/uland.taobao.com\/quan\/detail?sellerId=138722161&activityId=95d3e3f028d44d22bc0fdd17668677ea","seller_id":"","quan_id":"","quan_shengyu":"97000","quan_zhong":"100000","quan_ling":"0","quan_expired_time":"2018-09-28 23:59:59","quan_note":"180","quan_guid_content":"\u3010\u5168\u5e97\u94fa\u901a\u7528\u5377\u3011\u65b0\u52a0\u5761\u4ee3\u8d2d\u5c0fck\uff0c\u9ed1\u8272\u901a\u52e4\u624b\u63d0\u8033\u6735\u5305\uff0c\u6574\u4f53\u76ae\u8d28\u67d4\u8f6f\u8212\u9002\uff0c\u5305\u5305\u5ef6\u7eed\u4e86\u4e00\u5411\u968f\u6027\u7b80\u7ea6\u98ce\u683c\uff0c\u80cc\u8d77\u6765\u7b80\u7ea6\u6709\u4e2a\u6027\uff0c\u597d\u770b\u968f\u610f\u53c8\u767e\u642d\uff0c\u5973\u795e\u5fc5\u5907\u65f6\u5c1a\u968f\u4f60\u800c\u52a8~~","quan_qq_img":"http:\/\/images.jbkuan.com\/20180927\/1315b2952f4d2c470794bbb02c1f0854.jpg_250x250.jpg","src":"0","jhs":"0","tqg":"0","gold":"0","freight":"0","abroad":"1","flagship":"0"},{"id":"8993058","goods_name":"\u97e9\u56fd\u4e1c\u5927\u95e8\u4ee3\u8d2d\u8bbe\u8ba1\u5e08\u91d1\u5c5e\u73cd\u73e0\u8033\u73af\u5973 \u4f18\u96c5\u6c14\u8d28\u4e2a\u6027\u6c14\u8d28\u8033\u9489\u8033\u9970","goods_id":"573922971987","cate_id":"7","cate_name":"\u978b\u5305\u670d\u9970","goods_url":"https:\/\/detail.tmall.com\/item.htm?id=573922971987","pic":"http:\/\/img.alicdn.com\/imgextra\/i4\/1765467343\/TB2ld4rFVOWBuNjy0FiXXXFxVXa_!!1765467343.jpg","price":39,"price_after_coupons":34,"price_coupons":"5.0","sales":"3988","rate":"20.0","commission_type":"4","commission_type_name":null,"quan_link":"https:\/\/uland.taobao.com\/quan\/detail?sellerId=1765467343&activityId=8a1c873ddb72423c8f349bac62cd89e3","seller_id":"","quan_id":"","quan_shengyu":"9900","quan_zhong":"9999","quan_ling":"0","quan_expired_time":"2018-10-01 23:59:59","quan_note":"39","quan_guid_content":"\u97e9\u56fd\u4e1c\u5927\u95e8\u4ee3\u8d2d\u8bbe\u8ba1\u5e08\uff0c\u73cd\u73e0\u8033\u73af\uff0c\u4f18\u96c5\u6c14\u8d28\uff0c\u590d\u53e4\u6c14\u8d28\u8033\u6263\u8033\u9489\uff01\u6b63\u5706\u9753\u4e3d\uff0c\u5149\u6ed1\u5706\u6da6\uff0c","quan_qq_img":"http:\/\/images.jbkuan.com\/20180926\/4f2c867f3e65ad72fe8b338e8fd611a2.jpg_250x250.jpg","src":"0","jhs":"0","tqg":"0","gold":"1","freight":"0","abroad":"0","flagship":"0"},{"id":"8980356","goods_name":"\u65b0\u52a0\u5761\u4ee3\u8d2dCHRELS&KAIAH\u5973\u5305\u65b0\u6b3e\u5c0f CK2-9068060\u7ffb\u76d6\u7c89\u8272\u90ae\u5dee\u5305\u5973","goods_id":"575993228070","cate_id":"7","cate_name":"\u978b\u5305\u670d\u9970","goods_url":"https:\/\/detail.tmall.com\/item.htm?id=575993228070","pic":"http:\/\/gd3.alicdn.com\/imgextra\/i3\/138722161\/O1CN011RpmLqUPjfNWH6r_!!138722161.jpg","price":268,"price_after_coupons":188,"price_coupons":"80.0","sales":"1105","rate":"20.1","commission_type":"3","commission_type_name":"\u9e4a\u6865","quan_link":"https:\/\/uland.taobao.com\/quan\/detail?sellerId=138722161&activityId=95d3e3f028d44d22bc0fdd17668677ea","seller_id":"","quan_id":"","quan_shengyu":"100000","quan_zhong":"100000","quan_ling":"0","quan_expired_time":"2018-09-28 23:59:59","quan_note":"180","quan_guid_content":"\u3010\u5168\u5e97\u94fa\u901a\u7528\u5377\u3011\u65b0\u52a0\u5761\u5c0fCK\uff0c\uff0c\u6574\u4f53\u76ae\u8d28\u67d4\u8f6f\u8212\u9002\uff0c\u5305\u5305\u5ef6\u7eed\u4e86\u4e00\u5411\u968f\u6027\u7b80\u7ea6\u98ce\u683c\uff0c\u80cc\u8d77\u6765\u7b80\u7ea6\u6709\u4e2a\u6027\uff0c\u597d\u770b\u968f\u610f\u53c8\u767e\u642d\uff0c\u5973\u795e\u5fc5\u5907\u65f6\u5c1a\u968f\u4f60\u800c\u52a8~~","quan_qq_img":"http:\/\/images.jbkuan.com\/20180926\/6504a9407cdfcb7b4d9d6ef5aff8ed4b.jpg_250x250.jpg","src":"0","jhs":"0","tqg":"0","gold":"0","freight":"0","abroad":"1","flagship":"0"},{"id":"8976916","goods_name":"\u65b0\u52a0\u5761\u4ee3\u8d2dCHRELS&KAIAH\u5973\u5305\u5c0f CK2-2068063\u9152\u795e\u5c0f\u65b9\u5305\u767e\u642d\u94fe\u6761\u5305","goods_id":"576507722153","cate_id":"7","cate_name":"\u978b\u5305\u670d\u9970","goods_url":"https:\/\/detail.tmall.com\/item.htm?id=576507722153","pic":"http:\/\/img.alicdn.com\/imgextra\/i4\/138722161\/O1CN011RpmLtBGThlvI98_!!138722161.jpg","price":268,"price_after_coupons":188,"price_coupons":"80.0","sales":"3233","rate":"20.1","commission_type":"1","commission_type_name":"\u5b9a\u5411","quan_link":"https:\/\/uland.taobao.com\/quan\/detail?sellerId=138722161&activityId=95d3e3f028d44d22bc0fdd17668677ea","seller_id":"","quan_id":"","quan_shengyu":"100000","quan_zhong":"100000","quan_ling":"0","quan_expired_time":"2018-09-28 23:59:59","quan_note":"180","quan_guid_content":"\u3010\u5168\u5e97\u94fa\u901a\u7528\u5377\u3011\u65b0\u52a0\u5761\u4ee3\u8d2d\u5c0fCK\u7cbe\u9009\u4f18\u8d28\u9762\u6599\uff0c\u505a\u5de5\u7cbe\u81f4\uff0c\u5c0f\u8eab\u6750\u5927\u5bb9\u91cf\uff0c\u5c0f\u5de7\u5b9e\u7528\uff0c\u7b80\u7ea6\u767e\u642d\uff0c\u65f6\u5c1a\u51fa\u884c\uff0c\u5973\u795e\u5fc5\u5907\u4e4b\u9009\u3002","quan_qq_img":"http:\/\/images.jbkuan.com\/20180926\/50440c96b21499433e88c65b45bc1c50.jpg_250x250.jpg","src":"0","jhs":"0","tqg":"0","gold":"0","freight":"0","abroad":"1","flagship":"0"},{"id":"8963250","goods_name":"\u4ee3\u8d2d\u5de5\u88c5\u88e4\u7537\u5bbd\u677e\u6f6e\u724c\u5927\u7801\u957f\u88e4\u5b50\u8ff7\u5f69\u65e5\u7cfb\u76f4\u7b52\u7537\u58eb\u53e3\u888b\u4f11\u95f2\u88e4\u6f6e","goods_id":"575107330582","cate_id":"2","cate_name":"\u7537\u88c5","goods_url":"https:\/\/detail.tmall.com\/item.htm?id=575107330582","pic":"http:\/\/img.alicdn.com\/imgextra\/i2\/2007446250\/TB1ZCr6mOQnBKNjSZFmXXcApVXa_!!0-item_pic.jpg","price":370,"price_after_coupons":350,"price_coupons":"20.0","sales":"41","rate":"25.1","commission_type":"1","commission_type_name":"\u5b9a\u5411","quan_link":"https:\/\/uland.taobao.com\/quan\/detail?sellerId=2007446250&activityId=6eb04f68ce9248f59f238f3715478ef2","seller_id":"","quan_id":"","quan_shengyu":"4971","quan_zhong":"5000","quan_ling":"0","quan_expired_time":"2018-10-16 23:59:59","quan_note":"20.01","quan_guid_content":"\u65f6\u5c1a\u4f11\u95f2\u88e4\uff0c\u526a\u88c1\u7b80\u7ea6\u5927\u6c14\uff0c\u4fee\u8eab\u663e\u7626\uff0c\u4efb\u541b\u9009\u62e9\uff0c\u8f7b\u677e\u6f14\u7ece\u5c5e\u4e8e\u4f60\u7684\u968f\u6027\u81ea\u6211\u4f11\u95f2\u98ce\uff01\uff01","quan_qq_img":"http:\/\/images.jbkuan.com\/20180925\/6623ac143490a3e7b828e4bd9e4d1213.jpg_250x250.jpg","src":"0","jhs":"0","tqg":"0","gold":"1","freight":"0","abroad":"1","flagship":"0"},{"id":"8928172","goods_name":"\u97e9\u56fd\u4e1c\u5927\u95e8\u4ee3\u8d2d\u4e0d\u5bf9\u79f0\u7231\u5fc3\u7b80\u7ea6\u62fc\u8272\u8033\u73af\u5973\u957f\u6b3e\u6c14\u8d28\u5c0f\u7ea2\u5fc3\u663e\u7626\u8033\u5760","goods_id":"573752864472","cate_id":"7","cate_name":"\u978b\u5305\u670d\u9970","goods_url":"https:\/\/detail.tmall.com\/item.htm?id=573752864472","pic":"http:\/\/img.alicdn.com\/imgextra\/i3\/1765467343\/TB2G0WLxndYBeNkSmLyXXXfnVXa_!!1765467343.jpg","price":39,"price_after_coupons":34,"price_coupons":"5.0","sales":"1796","rate":"20.0","commission_type":"4","commission_type_name":null,"quan_link":"https:\/\/uland.taobao.com\/quan\/detail?sellerId=1765467343&activityId=4a9fffc3ffac4bb5af19b2d5139203fc","seller_id":"","quan_id":"","quan_shengyu":"8811","quan_zhong":"9999","quan_ling":"0","quan_expired_time":"2018-09-28 23:59:59","quan_note":"35","quan_guid_content":"\u7231\u5fc3\u7b80\u7ea6\u62fc\u8272\u8033\u73af\u5973\u957f\u6b3e\u6c14\u8d28\u5c0f\u7ea2\u5fc3\u663e\u7626\u8033\u5760\uff0c\u767e\u642d\u597d\u770b\u53c8\u5927\u65b9\u8fd8\u4e0d\u8fc7\u65f6\uff0c\u4e0d\u53ef\u9519\u8fc7\u54e6\uff01","quan_qq_img":"http:\/\/images.jbkuan.com\/20180924\/49b6f8d08d2abcd9be4a05e4f8afd3bd.jpg_250x250.jpg","src":"0","jhs":"0","tqg":"0","gold":"1","freight":"0","abroad":"0","flagship":"0"},{"id":"8902853","goods_name":"\u4ee3\u8d2d\u79cb\u5b63\u4f11\u95f2\u88e4\u7537\u5bbd\u677e\u6f6e\u6d41\u675f\u811a\u88e4\u5b50\u65f6\u5c1a\u767e\u642d\u65e5\u7cfb\u5927\u7801\u80d6\u5b50\u54c8\u4f26\u88e4\u6f6e","goods_id":"575928711635","cate_id":"2","cate_name":"\u7537\u88c5","goods_url":"https:\/\/detail.tmall.com\/item.htm?id=575928711635","pic":"http:\/\/img.alicdn.com\/imgextra\/i1\/2007446250\/TB1Ou8MqXooBKNjSZPhXXc2CXXa_!!0-item_pic.jpg","price":370,"price_after_coupons":350,"price_coupons":"20.0","sales":"21","rate":"25.1","commission_type":"1","commission_type_name":"\u5b9a\u5411","quan_link":"https:\/\/uland.taobao.com\/quan\/detail?sellerId=2007446250&activityId=6eb04f68ce9248f59f238f3715478ef2","seller_id":"","quan_id":"","quan_shengyu":"4981","quan_zhong":"5000","quan_ling":"0","quan_expired_time":"2018-10-16 23:59:59","quan_note":"20.01","quan_guid_content":"\u79cb\u5b63\u4f11\u95f2\u88e4\uff0c\u7537\u5bbd\u677e\u6f6e\u6d41\u675f\u811a\u88e4\u5b50\uff0c\u65f6\u5c1a\u767e\u642d\uff0c\u65e5\u7cfb\u5927\u7801\uff0c\u80d6\u5b50\u54c8\u4f26\u88e4\u6f6e\u3002","quan_qq_img":"http:\/\/images.jbkuan.com\/20180923\/90467374520386a7024d4530dd18fd9f.jpg_250x250.jpg","src":"0","jhs":"0","tqg":"0","gold":"1","freight":"0","abroad":"1","flagship":"0"}],"dialog":""}